market_reaction/__init__.py
market_reaction/categorizer.py
market_reaction/correlation.py
market_reaction/engine.py
market_reaction/reaction.py
market_reaction/types.py
market_reaction/universe.py
market_reaction/volume.py
truthtrader_market_reaction-0.1.0.dist-info/METADATA
truthtrader_market_reaction-0.1.0.dist-info/WHEEL
truthtrader_market_reaction-0.1.0.dist-info/RECORD
