Metadata-Version: 2.4
Name: truthtrader-market-reaction
Version: 0.1.0
Summary: Market reaction engine: compute price reactions at a given datetime with automatic biggest mover discovery by sector or market-wide.
Author: Bryan Clauss
Author-email: bryanclauss@gmail.com
Requires-Python: >=3.11,<4.0
Classifier: Programming Language :: Python :: 3
Classifier: Programming Language :: Python :: 3.11
Classifier: Programming Language :: Python :: 3.12
Classifier: Programming Language :: Python :: 3.13
Classifier: Programming Language :: Python :: 3.14
Requires-Dist: numpy (>=1.26.0,<2.0.0)
Requires-Dist: pandas (>=2.2.0,<3.0.0)
Requires-Dist: truthtrader-barvault (>=0.1.0,<0.2.0)
